lifefit/__init__.py
lifefit/app/app.py
lifefit/data/IRF/irf.txt
lifefit/data/IRF/irf_time_intensity.txt
lifefit/data/anisotropy/HH.txt
lifefit/data/anisotropy/HV.txt
lifefit/data/anisotropy/VH.txt
lifefit/data/anisotropy/VV.txt
lifefit/data/lifetime/Atto550_DNA.txt
lifefit/data/lifetime/Atto550_DNA_time_intensity.txt
lifefit/gui.py
lifefit/tcspc.py
lifefit-1.0.9.dist-info/LICENSE
lifefit-1.0.9.dist-info/METADATA
lifefit-1.0.9.dist-info/WHEEL
lifefit-1.0.9.dist-info/entry_points.txt
lifefit-1.0.9.dist-info/RECORD
