Metadata-Version: 2.1
Name: Lifefit
Version: 1.0.9
Summary: Reconvolution fitting of time-correlated single-photon (TCPSC) data
Home-page: https://rna-fretools.github.io/
License: MIT
Keywords: TCSPC,fluorescence
Author: Fabio Steffen
Author-email: fabio.steffen@chem.uzh.ch
Maintainer: Fabio Steffen
Maintainer-email: fabio.steffen@chem.uzh.ch
Requires-Python: >=3.10
Classifier: Framework :: Jupyter
Classifier: License :: OSI Approved :: GNU General Public License v3 or later (GPLv3+)
Classifier: License :: OSI Approved :: MIT License
Classifier: Operating System :: OS Independent
Classifier: Programming Language :: Python
Classifier: Programming Language :: Python :: 3
Classifier: Programming Language :: Python :: 3.10
Classifier: Programming Language :: Python :: 3.11
Classifier: Programming Language :: Python :: 3.12
Classifier: Programming Language :: Python :: 3.13
Classifier: Topic :: Scientific/Engineering :: Bio-Informatics
Requires-Dist: matplotlib (>=3.9.1,<4.0.0)
Requires-Dist: mkdocs (>=1.6.0,<2.0.0)
Requires-Dist: mkdocs-jupyter (>=0.24.8,<0.25.0)
Requires-Dist: mkdocs-material (>=9.5.29,<10.0.0)
Requires-Dist: mkdocstrings-python (>=1.10.7,<2.0.0)
Requires-Dist: numpy (>=2.0.0,<3.0.0)
Requires-Dist: plotly (>=5.22.0,<6.0.0)
Requires-Dist: requests (>=2.32.3,<3.0.0)
Requires-Dist: scipy (>=1.14.0,<2.0.0)
Requires-Dist: seaborn (>=0.13.2,<0.14.0)
Requires-Dist: streamlit (>=1.36.0,<2.0.0)
Requires-Dist: uncertainties (>=3.2.2,<4.0.0)
Project-URL: Documentation, https://rna-fretools.github.io/lifefit
Project-URL: Repository, https://github.com/RNA-FRETools/lifefit
